ospm/__init__.py
ospm/__main__.py
ospm/apps.py
ospm/cli.py
ospm/config.py
ospm/generate.py
ospm/vault.py
ospm-1.1.0.dist-info/METADATA
ospm-1.1.0.dist-info/WHEEL
ospm-1.1.0.dist-info/entry_points.txt
ospm-1.1.0.dist-info/licenses/LICENSE
ospm-1.1.0.dist-info/RECORD
