Metadata-Version: 2.4
Name: ospm
Version: 1.1.0
Summary: Open Source password manager
License-File: LICENSE
Author: Anvarys
Author-email: 105349498+Anvarys@users.noreply.github.com
Requires-Python: >=3.10,<4.0
Classifier: Programming Language :: Python :: 3
Classifier: Programming Language :: Python :: 3.10
Classifier: Programming Language :: Python :: 3.11
Classifier: Programming Language :: Python :: 3.12
Classifier: Programming Language :: Python :: 3.13
Classifier: Programming Language :: Python :: 3.14
Requires-Dist: argon2-cffi (>=25.1.0,<26.0.0)
Requires-Dist: click (>=8.3.1,<9.0.0)
Requires-Dist: clipboard (>=0.0.4,<0.0.5)
Requires-Dist: platformdirs (>=4.5.1,<5.0.0)
Requires-Dist: pynacl (>=1.6.1,<2.0.0)
Requires-Dist: textual (>=6.11.0,<7.0.0)
